CHANGELOG.md
startdomain/__init__.py
startdomain/apps.py
startdomain/management/commands/startdomain.py
startdomain/management/commands/templates/__init__.py
startdomain/management/commands/templates/admin.py
startdomain/management/commands/templates/apis.py
startdomain/management/commands/templates/apps.py
startdomain/management/commands/templates/models.py
startdomain/management/commands/templates/serializers.py
startdomain/management/commands/templates/tests.py
startdomain/management/commands/templates/urls.py
startdomain-0.2.6.dist-info/LICENSE
startdomain-0.2.6.dist-info/METADATA
startdomain-0.2.6.dist-info/WHEEL
startdomain-0.2.6.dist-info/RECORD
